<archimate:ArchimateDiagramModel
    xmlns:xsi="http://www.w3.org/2001/XMLSchema-instance"
    xmlns:archimate="http://www.archimatetool.com/archimate"
    name="OGP.1. Формирование плана разработки"
    id="793f4c40-a427-4e99-b5e7-486dc62a5c91">
  <children
      xsi:type="archimate:DiagramModelArchimateObject"
      id="fd3c2751-a48c-4f19-9809-82aec06dfcf0"
      font="1|Segoe UI Semibold|12.0|0|WINDOWS|1|-40|0|0|0|600|0|0|0|-52|3|2|1|34|Segoe UI Semibold"
      textAlignment="1"
      fillColor="#fffff0">
    <bounds
        x="15"
        y="10"
        width="816"
        height="181"/>
    <children
        xsi:type="archimate:DiagramModelArchimateObject"
        id="1d1e3214-ac81-40ee-a94c-c5cb06627a6e"
        font="1|Segoe UI|12.0|0|WINDOWS|1|-40|0|0|0|400|0|0|0|-52|3|2|1|34|Segoe UI"
        textAlignment="1"
        textPosition="1">
      <bounds
          y="40"
          width="816"
          height="56"/>
      <archimateElement
          xsi:type="archimate:BusinessProcess"
          href="BusinessProcess_7fec56ad-2241-496f-81b6-be3504a6022e.xml#7fec56ad-2241-496f-81b6-be3504a6022e"/>
    </children>
    <children
        xsi:type="archimate:DiagramModelArchimateObject"
        id="e79d9bc5-ee90-4ee7-a427-90f1a031b14b"
        font="1|Segoe UI|12.0|0|WINDOWS|1|-40|0|0|0|400|0|0|0|-52|3|2|1|34|Segoe UI"
        textAlignment="1"
        textPosition="1">
      <bounds
          y="95"
          width="816"
          height="31"/>
      <archimateElement
          xsi:type="archimate:BusinessProcess"
          href="BusinessProcess_df2034ee-4384-4536-b2bf-d5a3aba19fef.xml#df2034ee-4384-4536-b2bf-d5a3aba19fef"/>
    </children>
    <children
        xsi:type="archimate:DiagramModelArchimateObject"
        id="bc67438b-4faf-4291-8342-616bcfc1e58f"
        font="1|Segoe UI|12.0|0|WINDOWS|1|-40|0|0|0|400|0|0|0|-52|3|2|1|34|Segoe UI"
        textAlignment="1"
        textPosition="1">
      <bounds
          y="125"
          width="816"
          height="56"/>
      <archimateElement
          xsi:type="archimate:BusinessProcess"
          href="BusinessProcess_5cebed0c-1393-4076-93c2-a83f2bccc92a.xml#5cebed0c-1393-4076-93c2-a83f2bccc92a"/>
    </children>
    <archimateElement
        xsi:type="archimate:BusinessProcess"
        href="BusinessProcess_75bfbf7f-2200-4d9b-98e8-b1fe195ea2b6.xml#75bfbf7f-2200-4d9b-98e8-b1fe195ea2b6"/>
  </children>
  <children
      xsi:type="archimate:DiagramModelArchimateObject"
      id="383d0671-8f78-4c0f-8785-62af5c9f5ef5"
      font="1|Segoe UI Semibold|12.0|0|WINDOWS|1|-40|0|0|0|600|0|0|0|-52|3|2|1|34|Segoe UI Semibold"
      textAlignment="1"
      fillColor="#fffff0">
    <bounds
        x="15"
        y="240"
        width="816"
        height="181"/>
    <children
        xsi:type="archimate:DiagramModelArchimateObject"
        id="185f5e3e-b9f1-4ce1-b98b-34eb010f8b92"
        font="1|Segoe UI|12.0|0|WINDOWS|1|-40|0|0|0|400|0|0|0|-52|3|2|1|34|Segoe UI"
        textAlignment="1"
        textPosition="1">
      <bounds
          y="40"
          width="816"
          height="56"/>
      <archimateElement
          xsi:type="archimate:BusinessProcess"
          href="BusinessProcess_e4e1f59c-e8e3-4939-b28f-7082f9fbffdb.xml#e4e1f59c-e8e3-4939-b28f-7082f9fbffdb"/>
    </children>
    <children
        xsi:type="archimate:DiagramModelArchimateObject"
        id="1fc4a3cd-f77a-428f-8a72-0522e6fd7873"
        font="1|Segoe UI|12.0|0|WINDOWS|1|-40|0|0|0|400|0|0|0|-52|3|2|1|34|Segoe UI"
        textAlignment="1"
        textPosition="1">
      <bounds
          y="95"
          width="816"
          height="31"/>
      <archimateElement
          xsi:type="archimate:BusinessProcess"
          href="BusinessProcess_3dae1fb6-2e2f-4d12-bcec-e345b8b687cb.xml#3dae1fb6-2e2f-4d12-bcec-e345b8b687cb"/>
    </children>
    <children
        xsi:type="archimate:DiagramModelArchimateObject"
        id="16bdfbc5-4e9d-4621-9d0d-3e9b0fd3d124"
        font="1|Segoe UI|12.0|0|WINDOWS|1|-40|0|0|0|400|0|0|0|-52|3|2|1|34|Segoe UI"
        textAlignment="1"
        textPosition="1">
      <bounds
          y="125"
          width="816"
          height="56"/>
      <archimateElement
          xsi:type="archimate:BusinessProcess"
          href="BusinessProcess_0caf1811-15d4-42ef-87e8-9baf601a0620.xml#0caf1811-15d4-42ef-87e8-9baf601a0620"/>
    </children>
    <archimateElement
        xsi:type="archimate:BusinessProcess"
        href="BusinessProcess_d36aba17-24fe-40d4-85ad-078191203d63.xml#d36aba17-24fe-40d4-85ad-078191203d63"/>
  </children>
  <children
      xsi:type="archimate:DiagramModelArchimateObject"
      id="d1764ea8-fd84-414e-8a14-0b610c5d654e"
      font="1|Segoe UI Semibold|12.0|0|WINDOWS|1|-40|0|0|0|600|0|0|0|-52|3|2|1|34|Segoe UI Semibold"
      textAlignment="1"
      fillColor="#fffff0">
    <bounds
        x="15"
        y="465"
        width="816"
        height="216"/>
    <children
        xsi:type="archimate:DiagramModelArchimateObject"
        id="d0da3727-d71b-4f48-88a7-c5d6244631ee"
        font="1|Segoe UI|12.0|0|WINDOWS|1|-40|0|0|0|400|0|0|0|-52|3|2|1|34|Segoe UI"
        textAlignment="1"
        textPosition="1">
      <bounds
          y="40"
          width="816"
          height="31"/>
      <archimateElement
          xsi:type="archimate:BusinessProcess"
          href="BusinessProcess_bd0c9826-0e3b-42fa-92c0-254b94233d8c.xml#bd0c9826-0e3b-42fa-92c0-254b94233d8c"/>
    </children>
    <children
        xsi:type="archimate:DiagramModelArchimateObject"
        id="7fac3f1c-2882-4e84-9283-274b83133675"
        font="1|Segoe UI|12.0|0|WINDOWS|1|-40|0|0|0|400|0|0|0|-52|3|2|1|34|Segoe UI"
        textAlignment="1"
        textPosition="1">
      <bounds
          y="70"
          width="816"
          height="31"/>
      <archimateElement
          xsi:type="archimate:BusinessProcess"
          href="BusinessProcess_da0903d2-01f6-4e5f-ae72-246d8ba9458b.xml#da0903d2-01f6-4e5f-ae72-246d8ba9458b"/>
    </children>
    <children
        xsi:type="archimate:DiagramModelArchimateObject"
        id="87d9af23-bddd-47c3-8b69-bd9dab154d8f"
        font="1|Segoe UI|11.1|0|WINDOWS|1|-37|0|0|0|400|0|0|0|-52|3|2|1|34|Segoe UI"
        textAlignment="1"
        textPosition="1">
      <bounds
          y="100"
          width="816"
          height="31"/>
      <archimateElement
          xsi:type="archimate:BusinessProcess"
          href="BusinessProcess_fc90e5dc-fb17-4855-ad23-7dcf8517cb50.xml#fc90e5dc-fb17-4855-ad23-7dcf8517cb50"/>
    </children>
    <children
        xsi:type="archimate:DiagramModelArchimateObject"
        id="869ce63b-6c2a-4ca2-9b84-76ee6d6e3a91"
        font="1|Segoe UI|12.0|0|WINDOWS|1|-40|0|0|0|400|0|0|0|-52|3|2|1|34|Segoe UI"
        textAlignment="1"
        textPosition="1">
      <bounds
          y="130"
          width="816"
          height="31"/>
      <archimateElement
          xsi:type="archimate:BusinessProcess"
          href="BusinessProcess_81e50190-7680-4dd3-b22f-18bb4e1ba0e3.xml#81e50190-7680-4dd3-b22f-18bb4e1ba0e3"/>
    </children>
    <children
        xsi:type="archimate:DiagramModelArchimateObject"
        id="2da98671-0422-434f-bd96-ff1ad02aa97a"
        font="1|Segoe UI|11.1|0|WINDOWS|1|-37|0|0|0|400|0|0|0|-52|3|2|1|34|Segoe UI"
        textAlignment="1"
        textPosition="2">
      <bounds
          y="160"
          width="816"
          height="56"/>
      <archimateElement
          xsi:type="archimate:BusinessProcess"
          href="BusinessProcess_a42f286d-e9cc-4b82-a28d-c10f01ec9dc7.xml#a42f286d-e9cc-4b82-a28d-c10f01ec9dc7"/>
    </children>
    <archimateElement
        xsi:type="archimate:BusinessProcess"
        href="BusinessProcess_d7e96c79-c902-4502-9c89-f5e7aecf84d5.xml#d7e96c79-c902-4502-9c89-f5e7aecf84d5"/>
  </children>
  <children
      xsi:type="archimate:DiagramModelArchimateObject"
      id="caf0447d-609c-4e81-8e0c-fef9a1b5e1fe"
      font="1|Segoe UI Semibold|12.0|0|WINDOWS|1|-40|0|0|0|600|0|0|0|-52|3|2|1|34|Segoe UI Semibold"
      textAlignment="1"
      fillColor="#fffff0">
    <bounds
        x="15"
        y="720"
        width="816"
        height="246"/>
    <children
        xsi:type="archimate:DiagramModelArchimateObject"
        id="a8e2225a-f663-4685-9212-b6656732517b"
        font="1|Segoe UI|12.0|0|WINDOWS|1|-40|0|0|0|400|0|0|0|-52|3|2|1|34|Segoe UI"
        textAlignment="1"
        textPosition="1">
      <bounds
          y="75"
          width="816"
          height="31"/>
      <archimateElement
          xsi:type="archimate:BusinessProcess"
          href="BusinessProcess_4f729c13-23c5-486c-8bef-f43070472333.xml#4f729c13-23c5-486c-8bef-f43070472333"/>
    </children>
    <children
        xsi:type="archimate:DiagramModelArchimateObject"
        id="8880dd29-1760-416e-838f-62f0d48d179a"
        font="1|Segoe UI|12.0|0|WINDOWS|1|-40|0|0|0|400|0|0|0|-52|3|2|1|34|Segoe UI"
        textAlignment="1"
        textPosition="1">
      <bounds
          y="105"
          width="816"
          height="31"/>
      <archimateElement
          xsi:type="archimate:BusinessProcess"
          href="BusinessProcess_2cf9a366-156b-4fa5-8c52-abf97be9bc6d.xml#2cf9a366-156b-4fa5-8c52-abf97be9bc6d"/>
    </children>
    <children
        xsi:type="archimate:DiagramModelArchimateObject"
        id="2043e3a3-251b-4a2e-9f93-d1e1ccb25f7d"
        font="1|Segoe UI|12.0|0|WINDOWS|1|-40|0|0|0|400|0|0|0|-52|3|2|1|34|Segoe UI"
        textAlignment="1"
        textPosition="1">
      <bounds
          y="45"
          width="816"
          height="31"/>
      <archimateElement
          xsi:type="archimate:BusinessProcess"
          href="BusinessProcess_24dc80ce-77f8-4ed8-acc3-5fd061ef2372.xml#24dc80ce-77f8-4ed8-acc3-5fd061ef2372"/>
    </children>
    <children
        xsi:type="archimate:DiagramModelArchimateObject"
        id="f5e90223-f4e5-4624-af53-ca039d0c08f9"
        font="1|Segoe UI|12.0|0|WINDOWS|1|-40|0|0|0|400|0|0|0|-52|3|2|1|34|Segoe UI"
        textAlignment="1"
        textPosition="1">
      <bounds
          y="135"
          width="816"
          height="56"/>
      <archimateElement
          xsi:type="archimate:BusinessProcess"
          href="BusinessProcess_3f4e2d3c-2d41-4325-864c-a1f6fc0f3dee.xml#3f4e2d3c-2d41-4325-864c-a1f6fc0f3dee"/>
    </children>
    <children
        xsi:type="archimate:DiagramModelArchimateObject"
        id="50e4a739-1c35-41ed-b094-9d372de3c23d"
        font="1|Segoe UI|12.0|0|WINDOWS|1|-40|0|0|0|400|0|0|0|-52|3|2|1|34|Segoe UI"
        textAlignment="1"
        textPosition="1">
      <bounds
          y="190"
          width="816"
          height="56"/>
      <archimateElement
          xsi:type="archimate:BusinessProcess"
          href="BusinessProcess_54d7d3e2-6810-4226-ab4b-e319e7a72a50.xml#54d7d3e2-6810-4226-ab4b-e319e7a72a50"/>
    </children>
    <archimateElement
        xsi:type="archimate:BusinessProcess"
        href="BusinessProcess_3e380d6a-df43-4e92-9a52-3090bf666135.xml#3e380d6a-df43-4e92-9a52-3090bf666135"/>
  </children>
</archimate:ArchimateDiagramModel>
